data_mining_qa/__init__.py
data_mining_qa/qa.py
data_mining_qa-0.1.0.dist-info/METADATA
data_mining_qa-0.1.0.dist-info/WHEEL
data_mining_qa-0.1.0.dist-info/top_level.txt
data_mining_qa-0.1.0.dist-info/RECORD
