Metadata-Version: 2.1
Name: data_mining_qa
Version: 0.1.0
Summary: A simple library providing answers to common data mining questions.
Home-page: 
Author: Your Name
Author-email: your_email@example.com
Classifier: Programming Language :: Python :: 3
Classifier: License :: OSI Approved :: MIT License
Classifier: Operating System :: OS Independent
Requires-Python: >=3.6
